lato/__init__.py
lato/application.py
lato/application_module.py
lato/compositon.py
lato/dependency_provider.py
lato/message.py
lato/py.typed
lato/testing.py
lato/transaction_context.py
lato/types.py
lato/utils.py
lato-0.11.1.dist-info/LICENSE
lato-0.11.1.dist-info/METADATA
lato-0.11.1.dist-info/WHEEL
lato-0.11.1.dist-info/RECORD
