Metadata-Version: 2.1
Name: lato
Version: 0.11.1
Summary: Lato is a Python microframework designed for building modular monoliths and loosely coupled applications.
Home-page: https://github.com/pgorecki/lato
License: MIT
Author: Przemysław Górecki
Author-email: przemyslaw.gorecki@gmail.com
Requires-Python: >=3.9,<4.0
Classifier: License :: OSI Approved :: MIT License
Classifier: Operating System :: OS Independent
Classifier: Programming Language :: Python :: 3
Classifier: Programming Language :: Python :: 3.9
Classifier: Programming Language :: Python :: 3.10
Classifier: Programming Language :: Python :: 3.11
Classifier: Programming Language :: Python :: 3.12
Requires-Dist: mergedeep (>=1.3.4,<2.0.0)
Requires-Dist: pydantic (>=2.4.2,<3.0.0)
Requires-Dist: pytest-asyncio (>=0.23.5.post1,<0.24.0)
Project-URL: Bug Tracker, https://github.com/pgorecki/lato/issues
Project-URL: Documentation, https://lato.readthedocs.io
Project-URL: Repository, https://github.com/pgorecki/lato
